Metadata-Version: 2.4
Name: sdkwa-whatsapp-api
Version: 1.0.0
Summary: Python SDK for SDKWA WhatsApp HTTP API
Author-email: SDKWA Community <support@sdkwa.pro>
License: MIT
Project-URL: Homepage, https://sdkwa.pro
Project-URL: Documentation, https://docs.sdkwa.pro
Project-URL: Repository, https://github.com/sdkwa/whatsapp-api-client-python
Project-URL: Issues, https://github.com/sdkwa/whatsapp-api-client-python/issues
Keywords: whatsapp,sdkwa,api,python,sdk
Classifier: Development Status :: 5 - Production/Stable
Classifier: Intended Audience :: Developers
Classifier: License :: OSI Approved :: MIT License
Classifier: Operating System :: OS Independent
Classifier: Programming Language :: Python :: 3
Classifier: Programming Language :: Python :: 3.8
Classifier: Programming Language :: Python :: 3.9
Classifier: Programming Language :: Python :: 3.10
Classifier: Programming Language :: Python :: 3.11
Classifier: Programming Language :: Python :: 3.12
Classifier: Topic :: Communications :: Chat
Classifier: Topic :: Internet :: WWW/HTTP :: Dynamic Content
Classifier: Topic :: Software Development :: Libraries :: Python Modules
Requires-Python: >=3.8
License-File: LICENSE
Requires-Dist: requests>=2.25.0
Requires-Dist: typing-extensions>=4.0.0; python_version < "3.10"
Dynamic: license-file
